dataclass_utils/VERSION.py
dataclass_utils/__init__.py
dataclass_utils/_internal/__init__.py
dataclass_utils/_internal/shared.py
dataclass_utils/error.py
dataclass_utils/into_dataclass.py
dataclass_utils/py.typed
dataclass_utils/type_checker.py
dataclass_utils/typing.py
dataclass_utils-0.7.23.dist-info/LICENSE
dataclass_utils-0.7.23.dist-info/WHEEL
dataclass_utils-0.7.23.dist-info/METADATA
dataclass_utils-0.7.23.dist-info/RECORD
