Metadata-Version: 2.1
Name: dataclass-utils
Version: 0.7.23
Summary: 
Author: Yohei Tamura
Author-email: tamuhey@gmail.com
Requires-Python: >=3.7,<4.0
Classifier: Programming Language :: Python :: 3
Classifier: Programming Language :: Python :: 3.10
Classifier: Programming Language :: Python :: 3.7
Classifier: Programming Language :: Python :: 3.8
Classifier: Programming Language :: Python :: 3.9
Requires-Dist: typing-extensions (>=3.10)
